{
    "envfs": {
        "branch": "main",
        "description": "Fuse filesystem that returns symlinks to executables based on the PATH of the requesting process.",
        "homepage": "",
        "owner": "Mic92",
        "repo": "envfs",
        "rev": "42bed8a2959aea39ced7b117614f7d5e5126db51",
        "sha256": "0ifyfk4cc5qx3i9315v6mw4fk38gskj8mm7r8sgr99p1ngh2lwjr",
        "type": "tarball",
        "url": "https://github.com/Mic92/envfs/archive/42bed8a2959aea39ced7b117614f7d5e5126db51.tar.gz",
        "url_template": "https://github.com/<owner>/<repo>/archive/<rev>.tar.gz"
    },
    "niv": {
        "branch": "master",
        "description": "Easy dependency management for Nix projects",
        "homepage": "https://github.com/nmattia/niv",
        "owner": "nmattia",
        "repo": "niv",
        "rev": "e0ca65c81a2d7a4d82a189f1e23a48d59ad42070",
        "sha256": "1pq9nh1d8nn3xvbdny8fafzw87mj7gsmp6pxkdl65w2g18rmcmzx",
        "type": "tarball",
        "url": "https://github.com/nmattia/niv/archive/e0ca65c81a2d7a4d82a189f1e23a48d59ad42070.tar.gz",
        "url_template": "https://github.com/<owner>/<repo>/archive/<rev>.tar.gz"
    }
}
